[{"city_id": 165, "council_member": "Rex Richardson", "img_url": "https://www.citystats.xyz/images/cities/165/mayor"}, {"city_id": 165, "council_member": "Mary Zendejas", "img_url": "https://www.citystats.xyz/images/cities/165/city_council/1"}, {"city_id": 165, "council_member": "Cindy Allen", "img_url": "https://www.citystats.xyz/images/cities/165/city_council/2"}, {"city_id": 165, "council_member": "Kristina Duggan", "img_url": "https://www.citystats.xyz/images/cities/165/city_council/3"}, {"city_id": 165, "council_member": "Daryl Supernaw", "img_url": "https://www.citystats.xyz/images/cities/165/city_council/4"}, {"city_id": 165, "council_member": "Megan Kerr", "img_url": "https://www.citystats.xyz/images/cities/165/city_council/5"}, {"city_id": 165, "council_member": "Suely Saro", "img_url": "https://www.citystats.xyz/images/cities/165/city_council/6"}, {"city_id": 165, "council_member": "Roberto Uranga", "img_url": "https://www.citystats.xyz/images/cities/165/city_council/7"}, {"city_id": 165, "council_member": "Al Austin", "img_url": "https://www.citystats.xyz/images/cities/165/city_council/8"}, {"city_id": 165, "council_member": "Joni Ricks-Oddie", "img_url": "https://www.citystats.xyz/images/cities/165/city_council/9"}]