[{"city_id": 217, "council_member": "Curt Skoog", "img_url": null}, {"city_id": 217, "council_member": "Logan Heley", "img_url": null}, {"city_id": 217, "council_member": "Holly Grummert", "img_url": null}, {"city_id": 217, "council_member": "Paul Lyons", "img_url": null}, {"city_id": 217, "council_member": "Melissa Cheatham", "img_url": null}, {"city_id": 217, "council_member": "Jim Kite", "img_url": null}, {"city_id": 217, "council_member": "Tom Carignan", "img_url": null}, {"city_id": 217, "council_member": "Fred Spears", "img_url": null}, {"city_id": 217, "council_member": "Scott Mosher", "img_url": null}, {"city_id": 217, "council_member": "Faris Farassati", "img_url": null}, {"city_id": 217, "council_member": "Sam Passer", "img_url": null}, {"city_id": 217, "council_member": "Scott Hamblin", "img_url": null}, {"city_id": 217, "council_member": "Jeff Cox", "img_url": null}]